loguru_mypy/__init__.py
loguru_mypy-0.0.4.dist-info/LICENSE
loguru_mypy-0.0.4.dist-info/METADATA
loguru_mypy-0.0.4.dist-info/WHEEL
loguru_mypy-0.0.4.dist-info/top_level.txt
loguru_mypy-0.0.4.dist-info/RECORD
