Metadata-Version: 2.1
Name: loguru-mypy
Version: 0.0.4
Summary: UNKNOWN
Home-page: https://github.com/kornicameister/loguru-mypy
Author: Tomasz Trębski
Author-email: kornicameister@gmail.com
License: MIT
Platform: UNKNOWN
Requires-Python: >=3.6.0
Requires-Dist: typing-extensions
